README.txt
setup.py
collective/__init__.py
collective.discussionplus.egg-info/PKG-INFO
collective.discussionplus.egg-info/SOURCES.txt
collective.discussionplus.egg-info/dependency_links.txt
collective.discussionplus.egg-info/entry_points.txt
collective.discussionplus.egg-info/namespace_packages.txt
collective.discussionplus.egg-info/not-zip-safe
collective.discussionplus.egg-info/requires.txt
collective.discussionplus.egg-info/top_level.txt
collective/discussionplus/__init__.py
collective/discussionplus/browser.py
collective/discussionplus/configure.zcml
collective/discussionplus/indexers.py
collective/discussionplus/interfaces.py
collective/discussionplus/patches.py
collective/discussionplus/permissions.zcml
collective/discussionplus/tests.py
collective/discussionplus/browser_templates/commentsviewlet.pt
collective/discussionplus/browser_templates/review.pt
collective/discussionplus/profiles/default/actions.xml
collective/discussionplus/profiles/default/browserlayer.xml
collective/discussionplus/profiles/default/catalog.xml
collective/discussionplus/profiles/default/metadata.xml
collective/discussionplus/profiles/default/portal_atct.xml
collective/discussionplus/profiles/default/rolemap.xml
collective/discussionplus/profiles/default/workflows.xml
collective/discussionplus/profiles/default/workflows/comment_review_workflow/definition.xml
docs/HISTORY.txt
docs/INSTALL.txt
docs/LICENSE.GPL
docs/LICENSE.txt