Metadata-Version: 1.0
Name: collective.discussionplus
Version: 1.0b2
Summary: Augments the standard Plone discussion tool to add basic approvals workflow, and ibetter indexing of comment metadata (number of comments, who has commented?)
Home-page: http://pypi.python.org/pypi/collective.discussionplus
Author: Martin Aspeli
Author-email: optilude@gmail.com
License: GPL
Keywords: plone discussion commenting
Platform: UNKNOWN
Classifier: Framework :: Plone
Classifier: Programming Language :: Python
Classifier: Topic :: Software Development :: Libraries :: Python Modules
